poocontab/__init__.py
poocontab/calcular_balanco.py
poocontab/calcular_rescisao.py
poocontab/exportar_pdf.py
poocontab/grafico.py
poocontab/poocontab.py
poocontab/registrar_transacao.py
poocontab-8.1.0.dist-info/METADATA
poocontab-8.1.0.dist-info/WHEEL
poocontab-8.1.0.dist-info/top_level.txt
poocontab-8.1.0.dist-info/RECORD
