Metadata-Version: 2.1
Name: poocontab
Version: 8.1.0
Summary: Pacote de teste
Author: crisly
Author-email: crislymaria21@gmail.com
Keywords: python,cont
Classifier: Development Status :: 3 - Alpha
Requires-Dist: numpy
Requires-Dist: matplotlib
Requires-Dist: fpdf
